pyBruker-1.1.3.data/scripts/brkraw
pybruker/__init__.py
pybruker/pybruker.py
test/__init__.py
test/test_transform.py
pyBruker-1.1.3.dist-info/LICENSE
pyBruker-1.1.3.dist-info/METADATA
pyBruker-1.1.3.dist-info/WHEEL
pyBruker-1.1.3.dist-info/top_level.txt
pyBruker-1.1.3.dist-info/RECORD
