Metadata-Version: 2.1
Name: pyBruker
Version: 1.1.3
Summary: Python Bruker Raw Data Handler
Home-page: https://dvm-shlee.github.io
Author: SungHo Lee
Author-email: shlee@unc.edu
License: GNLv3
Keywords: Bruker Raw Data Handler
Platform: UNKNOWN
Classifier: Development Status :: 4 - Beta
Classifier: Intended Audience :: Science/Research
Classifier: Topic :: Scientific/Engineering :: Information Analysis
Classifier: Natural Language :: English
Classifier: Programming Language :: Python :: 2.7
Requires-Dist: nibabel
Requires-Dist: numpy
Requires-Dist: xlrd
Requires-Dist: openpyxl
